config/__init__.py
config/asgi.py
config/settings.py
config/urls.py
config/wsgi.py
django_creta_auth/__init__.py
django_creta_auth/apps.py
django_creta_auth/gateway.py
django_creta_auth/serializers.py
django_creta_auth/test_gateway.py
django_creta_auth/tests.py
django_creta_auth/urls.py
django_creta_auth/views.py
django_creta_auth/migrations/__init__.py
django_creta_auth-0.2.1.dist-info/LICENSE
django_creta_auth-0.2.1.dist-info/METADATA
django_creta_auth-0.2.1.dist-info/WHEEL
django_creta_auth-0.2.1.dist-info/top_level.txt
django_creta_auth-0.2.1.dist-info/RECORD
